BR23021UNO/__init__.py
BR23021UNO/biseccion.py
BR23021UNO/crammer.py
BR23021UNO/descomposicion_lu.py
BR23021UNO/eliminacion_gauss.py
BR23021UNO/gauss_jordan.py
BR23021UNO/gauss_seidel.py
BR23021UNO/jacobi.py
br23021uno-1.5.0.dist-info/METADATA
br23021uno-1.5.0.dist-info/WHEEL
br23021uno-1.5.0.dist-info/top_level.txt
br23021uno-1.5.0.dist-info/RECORD
