Metadata-Version: 2.1
Name: br23021uno
Version: 1.5.0
Summary: Librería para resolver sistemas de ecuaciones lineales y no lineales.
Author: Joyser Leonel Barrera Romero
Classifier: Programming Language :: Python :: 3
Classifier: License :: OSI Approved :: MIT License
Classifier: Operating System :: OS Independent
Requires-Python: >=3.7
Requires-Dist: numpy
